MANIFEST.in
setup.py
django_metafeed/__init__.py
django_metafeed/feeds.py
django_metafeed/models.py
django_metafeed/tests.py
django_metafeed/testsettings.py
django_metafeed/urls.py
django_metafeed/views.py
django_metafeed.egg-info/PKG-INFO
django_metafeed.egg-info/SOURCES.txt
django_metafeed.egg-info/dependency_links.txt
django_metafeed.egg-info/not-zip-safe
django_metafeed.egg-info/top_level.txt