Metadata-Version: 1.0
Name: django-metafeed
Version: 0.1.0
Summary: Django feed aggregator, to merge few feeds into the one.
Home-page: http://github.com/svetlyak40wt/django-metafeed/
Author: Alexander Artemenko
Author-email: svetlyak.40wt@gmail.com
License: New BSD License
Keywords: django apps
Platform: UNKNOWN
Classifier: Development Status :: 2 - Pre-Alpha
Classifier: Environment :: Plugins
Classifier: Framework :: Django
Classifier: Intended Audience :: Developers
Classifier: License :: OSI Approved :: BSD License
Classifier: Programming Language :: Python
Classifier: Topic :: Software Development :: Libraries :: Python Modules
